clang_helpers/data_frame.py
clang_helpers/__init__.py
clang_helpers/clang/cindex.py
clang_helpers/clang/enumerations.py
clang_helpers/clang/__init__.py
clang_helpers/libclang/libclang-3.5.i686.so
clang_helpers/libclang/libclang-3.5.x86_64.so
clang_helpers/libclang/libclang.dll
clang_helpers/libclang/libclang.dylib
clang_helpers/libclang/VERSION.txt
clang_helpers-0.3.dist-info/DESCRIPTION.rst
clang_helpers-0.3.dist-info/METADATA
clang_helpers-0.3.dist-info/metadata.json
clang_helpers-0.3.dist-info/pbr.json
clang_helpers-0.3.dist-info/RECORD
clang_helpers-0.3.dist-info/top_level.txt
clang_helpers-0.3.dist-info/WHEEL
