Metadata-Version: 2.0
Name: clang-helpers
Version: 0.3
Summary: High-level API using `clang` module to provide static C++ class introspection.
Home-page: https://github.com/wheeler-microfluidics/clang_helpers
Author: Christian Fobel
Author-email: UNKNOWN
License: GPL
Keywords: c++ clang introspection
Platform: UNKNOWN
